Metadata-Version: 2.1
Name: py-discord-api
Version: 0.0.1
Summary: Python's Library for Discord API
Author: Koll
License-File: license.txt
